Metadata-Version: 2.1
Name: PyJsonX
Version: 0.0.2
Summary: PyJsonX data visualization of regression, classification and distribution
Home-page: https://github.com/nnnnnnn0090/PyJsonX
Download-URL: https://github.com/nnnnnnn0090/PyJsonX
Author: nnnnnnn0090
Author-email: nnnnnnn0090@gmail.com
Maintainer: nnnnnnn0090
Maintainer-email: nnnnnnn0090@gmail.com
License: MIT
Classifier: Intended Audience :: Developers
Classifier: License :: OSI Approved :: MIT License
Classifier: Programming Language :: Python :: 3
Classifier: Programming Language :: Python :: 3.6
Classifier: Programming Language :: Python :: 3.7
Classifier: Programming Language :: Python :: 3.8
Classifier: Programming Language :: Python :: 3.9
Classifier: Programming Language :: Python :: 3 :: Only
Classifier: Topic :: Software Development :: Libraries
Classifier: Topic :: Software Development :: Libraries :: Python Modules
Classifier: Topic :: Utilities
Requires-Python: >=3.0
License-File: LICENSE
